supercheetah_tuner/__init__.py
supercheetah_tuner/core.py
supercheetah_tuner-0.1.2.dist-info/METADATA
supercheetah_tuner-0.1.2.dist-info/WHEEL
supercheetah_tuner-0.1.2.dist-info/top_level.txt
supercheetah_tuner-0.1.2.dist-info/RECORD
