Metadata-Version: 2.4
Name: supercheetah_tuner
Version: 0.1.2
Summary: Nature-inspired hyperparameter tuning with Cheetah optimizer
Home-page: https://github.com/UjwalWtg/supercheetah-tuner
Author: Ujwal Watgule
Classifier: Programming Language :: Python :: 3
Classifier: License :: OSI Approved :: MIT License
Requires-Python: >=3.7
Requires-Dist: numpy>=1.20
Requires-Dist: scikit-learn>=1.0
Dynamic: author
Dynamic: classifier
Dynamic: description
Dynamic: description-content-type
Dynamic: home-page
Dynamic: requires-dist
Dynamic: requires-python
Dynamic: summary
